webrandints/__init__.py
webrandints-1.5.dist-info/LICENSE.txt
webrandints-1.5.dist-info/METADATA
webrandints-1.5.dist-info/WHEEL
webrandints-1.5.dist-info/top_level.txt
webrandints-1.5.dist-info/RECORD
