Metadata-Version: 2.1
Name: webrandints
Version: 1.5
Summary: Module to get randints from www.random.org
Home-page: UNKNOWN
Author: Vadim Fedulov
Author-email: vadimfedulov035@gmail.com
License: GNU GPL v3
Keywords: web,random,ints
Platform: UNKNOWN
License-File: LICENSE.txt
Requires-Dist: requests
